<?xml version="1.0" encoding="UTF-8" ?>
<!DOCTYPE WMT_MS_Capabilities SYSTEM "http://schemas.opengis.net/wms/1.1.1/WMS_MS_Capabilities.dtd">
  <WMT_MS_Capabilities version="1.1.1">
      <Service>
        <Name>OGC:WMS</Name>
        <Title>Web Map Service wms_berggrunden</Title>
        <Abstract>ArcIMS 9.1.0wms_berggrunden Web Map Service</Abstract>
          <KeywordList>
            <Keyword>ArcIMS</Keyword>
        </KeywordList>
        <OnlineResource xmlns:xlink="http://www.w3.org/1999/xlink" xlink:href="http://maps.sgu.se:80/wmsconnector/com.esri.wms.Esrimap/wms_berggrunden?" xlink:type="simple" />
          <ContactInformation>
              <ContactPersonPrimary>
                <ContactPerson>Kundtjänst</ContactPerson>
                <ContactOrganization />
            </ContactPersonPrimary>
            <ContactPosition />
              <ContactAddress>
                <AddressType>postal</AddressType>
                <Address />
                <City />
                <StateOrProvince />
                <PostCode />
                <Country />
            </ContactAddress>
            <ContactVoiceTelephone />
            <ContactFacsimileTelephone />
            <ContactElectronicMailAddress />
        </ContactInformation>
        <Fees>none</Fees>
        <AccessConstraints>none</AccessConstraints>
    </Service>
      <Capability>
          <Request>
              <GetCapabilities>
                <Format>application/vnd.ogc.wms_xml</Format>
                  <DCPType>
                      <HTTP>
                          <Get>
                            <OnlineResource xmlns:xlink="http://www.w3.org/1999/xlink" xlink:href="http://maps.sgu.se:80/wmsconnector/com.esri.wms.Esrimap/wms_berggrunden?" xlink:type="simple" />
                        </Get>
                    </HTTP>
                </DCPType>
            </GetCapabilities>
              <GetMap>
                <Format>image/png</Format>
                <Format>image/jpeg</Format>
                  <DCPType>
                      <HTTP>
                          <Get>
                            <OnlineResource xmlns:xlink="http://www.w3.org/1999/xlink" xlink:href="http://maps.sgu.se:80/wmsconnector/com.esri.wms.Esrimap/wms_berggrunden?" xlink:type="simple" />
                        </Get>
                    </HTTP>
                </DCPType>
            </GetMap>
              <GetFeatureInfo>
                <Format>application/vnd.ogc.wms_xml</Format>
                <Format>text/xml</Format>
                <Format>text/html</Format>
                <Format>text/plain</Format>
                  <DCPType>
                      <HTTP>
                          <Get>
                            <OnlineResource xmlns:xlink="http://www.w3.org/1999/xlink" xlink:href="http://maps.sgu.se:80/wmsconnector/com.esri.wms.Esrimap/wms_berggrunden?" xlink:type="simple" />
                        </Get>
                    </HTTP>
                </DCPType>
            </GetFeatureInfo>
        </Request>
          <Exception>
            <Format>application/vnd.ogc.se_xml</Format>
            <Format>application/vnd.ogc.se_inimage</Format>
            <Format>application/vnd.ogc.se_blank</Format>
        </Exception>
          <Layer queryable="0" opaque="0" noSubsets="0">
            <Title>wms_berggrunden</Title>
            <SRS>EPSG:4326</SRS>
            <SRS>EPSG:2400</SRS>
            <SRS>EPSG:4267</SRS>
            <SRS>EPSG:4269</SRS>
            <LatLonBoundingBox minx="8.2932562156" miny="55.0936176387" maxx="25.7869060103" maxy="69.1648892636" />
            <BoundingBox SRS="EPSG:2400" minx="1221160.5" miny="6137200" maxx="1883671.25" maxy="7670773" />
              <Layer queryable="1" opaque="0" noSubsets="0">
                  <Name>2</Name>
                  <Title>TODO!SGUBergarter, förenklad indelning</Title>
                  <SRS>EPSG:900913</SRS>
                  <LatLonBoundingBox minx="8.8302267377" miny="55.2154959248" maxx="25.3704820082" maxy="69.127001876" />
              </Layer>
              <Layer queryable="1" opaque="0" noSubsets="0">
                  <Name>6</Name>
                  <Title>TODO!SGUBergarter, detaljerad indelning</Title>
                  <SRS>EPSG:900913</SRS>
                  <LatLonBoundingBox minx="8.2932562156" miny="55.0936176387" maxx="25.7869060103" maxy="69.1648892636" />
                  <ScaleHint min="0" max="NaN" />
              </Layer>
              <Layer queryable="1" opaque="0" noSubsets="0">
                  <Name>BK:SGU_Diabasgangar</Name>
                  <Title>Diabasgångar</Title>
                  <SRS>EPSG:900913</SRS>
                  <LatLonBoundingBox minx="10.0928301143" miny="55.3715385988" maxx="19.8145713575" maxy="64.8765150505" />
              </Layer>
              <Layer queryable="1" opaque="0" noSubsets="0">
                  <Name>BK:SGU_Tektonik</Name>
                  <Title>Tektonik</Title>
                  <SRS>EPSG:900913</SRS>
                  <LatLonBoundingBox minx="9.6350717789" miny="55.2833858325" maxx="23.9616911034" maxy="69.1264465768" />
              </Layer>
        </Layer>
    </Capability>
</WMT_MS_Capabilities>
